cosmian_py_ggml-1.2.0.dist-info/METADATA
cosmian_py_ggml-1.2.0.dist-info/LICENSE
cosmian_py_ggml-1.2.0.dist-info/RECORD
cosmian_py_ggml-1.2.0.dist-info/WHEEL
cosmian_py_ggml/falcon.py
cosmian_py_ggml/mpt.py
cosmian_py_ggml/gpt_neox.py
cosmian_py_ggml/ggml_shared_lib.py
cosmian_py_ggml/libggml-bindings.so
cosmian_py_ggml/py.typed
cosmian_py_ggml/__init__.py
