Metadata-Version: 2.1
Name: cosmian-py-ggml
Version: 1.2.0
Summary: Python bindings for GGML
License: MIT
Author: Hugo Rosenkranz-Costa
Author-email: hugo.rosenkranz@cosmian.com
Requires-Python: >=3.8,<4.0
Classifier: License :: OSI Approved :: MIT License
Classifier: Programming Language :: Python :: 3
Classifier: Programming Language :: Python :: 3.8
Classifier: Programming Language :: Python :: 3.9
Classifier: Programming Language :: Python :: 3.10
Classifier: Programming Language :: Python :: 3.11
